docs/developer-guide.md
docs/gen_ref_nav.py
docs/index.md
docs/install.md
docs/user-guide.md
safe_autonomy_dynamics/__init__.py
safe_autonomy_dynamics/base_models.py
safe_autonomy_dynamics/cwh/__init__.py
safe_autonomy_dynamics/cwh/point_model.py
safe_autonomy_dynamics/cwh/rotational_model.py
safe_autonomy_dynamics/cwh/sixdof_model.py
safe_autonomy_dynamics/cwh/sun_model.py
safe_autonomy_dynamics/dubins.py
safe_autonomy_dynamics/external/__init__.py
safe_autonomy_dynamics/external/aerobench/__init__.py
safe_autonomy_dynamics/external/aerobench/controlled_f16.py
safe_autonomy_dynamics/external/aerobench/lowlevel/__init__.py
safe_autonomy_dynamics/external/aerobench/lowlevel/adc.py
safe_autonomy_dynamics/external/aerobench/lowlevel/cl.py
safe_autonomy_dynamics/external/aerobench/lowlevel/clf16.py
safe_autonomy_dynamics/external/aerobench/lowlevel/cm.py
safe_autonomy_dynamics/external/aerobench/lowlevel/cn.py
safe_autonomy_dynamics/external/aerobench/lowlevel/conf16.py
safe_autonomy_dynamics/external/aerobench/lowlevel/cx.py
safe_autonomy_dynamics/external/aerobench/lowlevel/cy.py
safe_autonomy_dynamics/external/aerobench/lowlevel/cz.py
safe_autonomy_dynamics/external/aerobench/lowlevel/dampp.py
safe_autonomy_dynamics/external/aerobench/lowlevel/dlda.py
safe_autonomy_dynamics/external/aerobench/lowlevel/dldr.py
safe_autonomy_dynamics/external/aerobench/lowlevel/dnda.py
safe_autonomy_dynamics/external/aerobench/lowlevel/dndr.py
safe_autonomy_dynamics/external/aerobench/lowlevel/low_level_controller.py
safe_autonomy_dynamics/external/aerobench/lowlevel/morellif16.py
safe_autonomy_dynamics/external/aerobench/lowlevel/pdot.py
safe_autonomy_dynamics/external/aerobench/lowlevel/rtau.py
safe_autonomy_dynamics/external/aerobench/lowlevel/subf16_model.py
safe_autonomy_dynamics/external/aerobench/lowlevel/tgear.py
safe_autonomy_dynamics/external/aerobench/lowlevel/thrust.py
safe_autonomy_dynamics/external/aerobench/util.py
safe_autonomy_dynamics/integrators.py
safe_autonomy_dynamics-1.2.3.dist-info/LICENSE
safe_autonomy_dynamics-1.2.3.dist-info/METADATA
safe_autonomy_dynamics-1.2.3.dist-info/WHEEL
safe_autonomy_dynamics-1.2.3.dist-info/RECORD
