Metadata-Version: 2.1
Name: safe-autonomy-dynamics
Version: 1.2.3
Summary: The safe-autonomy-dynamics package provides an API for dynamic systems supported by a library of common functions used to access and update system dynamics.
Home-page: https://github.com/act3-ace/safe-autonomy-dynamics.git
Author: Charles Keating
Author-email: Charles.Keating@udri.udayton.edu
Requires-Python: >=3.9,<3.13
Classifier: Operating System :: OS Independent
Classifier: Programming Language :: Python :: 3
Classifier: Programming Language :: Python :: 3.9
Classifier: Programming Language :: Python :: 3.10
Classifier: Programming Language :: Python :: 3.11
Classifier: Programming Language :: Python :: 3.12
Provides-Extra: jax
Requires-Dist: jax[cpu] (==0.4.26) ; extra == "jax"
Requires-Dist: numpy (>=1.23.5,<2.0.0)
Requires-Dist: pint (>=0.22,<0.23)
Requires-Dist: pydantic (>=2.6.2,<3.0.0)
Requires-Dist: scipy (>=1.10.0)
Project-URL: Documentation, https://github.com/act3-ace/safe-autonomy-dynamics/docs
Project-URL: Repository, https://github.com/act3-ace/safe-autonomy-dynamics.git
